pyfunctions/__init__.py
pyfunctions/fun.py
pyfunctions-2020.6.17.13.47.45.dist-info/METADATA
pyfunctions-2020.6.17.13.47.45.dist-info/WHEEL
pyfunctions-2020.6.17.13.47.45.dist-info/top_level.txt
pyfunctions-2020.6.17.13.47.45.dist-info/RECORD
