Metadata-Version: 2.1
Name: pyfunctions
Version: 2020.6.17.13.47.45
Summary: This project contains many functions that can be used in daily development.
Home-page: https://github.com/broholens/pyfunctions
Author: zz
Author-email: zzwcng@126.com
License: MIT
Platform: UNKNOWN
Classifier: License :: OSI Approved :: MIT License
Classifier: Programming Language :: Python
Classifier: Programming Language :: Python :: 3
Classifier: Programming Language :: Python :: 3.6
Requires-Python: >=3.6.0
Requires-Dist: chardet
Requires-Dist: requests
Requires-Dist: html2text
Requires-Dist: w3lib
Requires-Dist: lxml
Requires-Dist: faker
Requires-Dist: selenium
